{
  "db_name": "MySQL",
  "query": "SELECT id, invoice_no, period_start, period_end, total_amount,\n                  status, items, created_at, issued_at, paid_at\n           FROM invoices WHERE id = ? AND user_id = ?",
  "describe": {
    "columns": [
      {
        "ordinal": 0,
        "name": "id",
        "type_info": {
          "type": "String",
          "flags": "NOT_NULL | PRIMARY_KEY | NO_DEFAULT_VALUE",
          "char_set": 224,
          "max_size": 144
        }
      },
      {
        "ordinal": 1,
        "name": "invoice_no",
        "type_info": {
          "type": "VarString",
          "flags": "NOT_NULL | UNIQUE_KEY | NO_DEFAULT_VALUE",
          "char_set": 224,
          "max_size": 256
        }
      },
      {
        "ordinal": 2,
        "name": "period_start",
        "type_info": {
          "type": "Date",
          "flags": "NOT_NULL | BINARY | NO_DEFAULT_VALUE",
          "char_set": 63,
          "max_size": 10
        }
      },
      {
        "ordinal": 3,
        "name": "period_end",
        "type_info": {
          "type": "Date",
          "flags": "NOT_NULL | BINARY | NO_DEFAULT_VALUE",
          "char_set": 63,
          "max_size": 10
        }
      },
      {
        "ordinal": 4,
        "name": "total_amount",
        "type_info": {
          "type": "NewDecimal",
          "flags": "NOT_NULL",
          "char_set": 63,
          "max_size": 14
        }
      },
      {
        "ordinal": 5,
        "name": "status",
        "type_info": {
          "type": "String",
          "flags": "NOT_NULL | MULTIPLE_KEY | ENUM",
          "char_set": 224,
          "max_size": 24
        }
      },
      {
        "ordinal": 6,
        "name": "items",
        "type_info": {
          "type": "Json",
          "flags": "BLOB | BINARY",
          "char_set": 63,
          "max_size": 4294967295
        }
      },
      {
        "ordinal": 7,
        "name": "created_at",
        "type_info": {
          "type": "Datetime",
          "flags": "NOT_NULL | BINARY",
          "char_set": 63,
          "max_size": 19
        }
      },
      {
        "ordinal": 8,
        "name": "issued_at",
        "type_info": {
          "type": "Datetime",
          "flags": "BINARY",
          "char_set": 63,
          "max_size": 19
        }
      },
      {
        "ordinal": 9,
        "name": "paid_at",
        "type_info": {
          "type": "Datetime",
          "flags": "BINARY",
          "char_set": 63,
          "max_size": 19
        }
      }
    ],
    "parameters": {
      "Right": 2
    },
    "nullable": [
      false,
      false,
      false,
      false,
      false,
      false,
      true,
      false,
      true,
      true
    ]
  },
  "hash": "1f1eb749a3251c83fd9e5697ca5bc8e0e485273c2778a32bc06150245d738468"
}
